MANIFEST.in
README.rst
setup.py
docs/HISTORY.txt
docs/LICENSE.GPL
docs/LICENSE.txt
ftw/__init__.py
ftw.theming.egg-info/PKG-INFO
ftw.theming.egg-info/SOURCES.txt
ftw.theming.egg-info/dependency_links.txt
ftw.theming.egg-info/entry_points.txt
ftw.theming.egg-info/namespace_packages.txt
ftw.theming.egg-info/not-zip-safe
ftw.theming.egg-info/requires.txt
ftw.theming.egg-info/top_level.txt
ftw/theming/__init__.py
ftw/theming/compiler.py
ftw/theming/configure.zcml
ftw/theming/exceptions.py
ftw/theming/extensions.py
ftw/theming/header.py
ftw/theming/hooks.py
ftw/theming/icons.py
ftw/theming/interfaces.py
ftw/theming/meta.py
ftw/theming/meta.zcml
ftw/theming/profileinfo.py
ftw/theming/registry.py
ftw/theming/resource.py
ftw/theming/resources.zcml
ftw/theming/testing.py
ftw/theming/utils.py
ftw/theming/variables.py
ftw/theming/Extensions/install.py
ftw/theming/browser/__init__.py
ftw/theming/browser/configure.zcml
ftw/theming/browser/controlpanel.py
ftw/theming/browser/icons.py
ftw/theming/browser/theming_css.py
ftw/theming/browser/theming_variables.py
ftw/theming/browser/templates/icons.pt
ftw/theming/browser/templates/resources.pt
ftw/theming/browser/templates/variables.pt
ftw/theming/profiles/base/cssregistry.xml
ftw/theming/profiles/base/metadata.xml
ftw/theming/profiles/default/browserlayer.xml
ftw/theming/profiles/default/controlpanel.xml
ftw/theming/profiles/default/metadata.xml
ftw/theming/profiles/uninstall/browserlayer.xml
ftw/theming/resources/font-awesome/css/font-awesome.css
ftw/theming/resources/font-awesome/css/font-awesome.min.css
ftw/theming/resources/font-awesome/fonts/FontAwesome.otf
ftw/theming/resources/font-awesome/fonts/fontawesome-webfont.eot
ftw/theming/resources/font-awesome/fonts/fontawesome-webfont.svg
ftw/theming/resources/font-awesome/fonts/fontawesome-webfont.ttf
ftw/theming/resources/font-awesome/fonts/fontawesome-webfont.woff
ftw/theming/resources/font-awesome/fonts/fontawesome-webfont.woff2
ftw/theming/resources/font-awesome/less/animated.less
ftw/theming/resources/font-awesome/less/bordered-pulled.less
ftw/theming/resources/font-awesome/less/core.less
ftw/theming/resources/font-awesome/less/fixed-width.less
ftw/theming/resources/font-awesome/less/font-awesome.less
ftw/theming/resources/font-awesome/less/icons.less
